quant1x/__init__.py
quant1x/device.py
quant1x/devp.py
quant1x/network.py
quant1x/numerics.py
quant1x/system.py
quant1x/version.py
quant1x/cache/__init__.py
quant1x/cache/f10.py
quant1x/cache/market.py
quant1x/cache/sector.py
quant1x/cache/security.py
quant1x/config/__init__.py
quant1x/config/config.py
quant1x/datasets/__init__.py
quant1x/datasets/kline.py
quant1x/datasets/trans.py
quant1x/datasets/xdxr.py
quant1x/encoding/__init__.py
quant1x/encoding/yaml.py
quant1x/exchange/__init__.py
quant1x/exchange/calendar.py
quant1x/exchange/code.py
quant1x/exchange/margin_trading.py
quant1x/exchange/markets.py
quant1x/exchange/security.py
quant1x/exchange/session.py
quant1x/exchange/timestamp.py
quant1x/factors/__init__.py
quant1x/factors/base.py
quant1x/factors/f10.py
quant1x/factors/financial_report.py
quant1x/factors/notice.py
quant1x/factors/safety_score.py
quant1x/factors/share_holder.py
quant1x/formula/__init__.py
quant1x/formula/formula.py
quant1x/formula/formula_plus.py
quant1x/indicators/__init__.py
quant1x/indicators/cdtd.py
quant1x/indicators/f89k.py
quant1x/indicators/hjk.py
quant1x/indicators/ma1x.py
quant1x/indicators/p2fb.py
quant1x/level1/__init__.py
quant1x/level1/block_info.py
quant1x/level1/block_meta.py
quant1x/level1/client.py
quant1x/level1/config.py
quant1x/level1/finance_info.py
quant1x/level1/heartbeat.py
quant1x/level1/hello1.py
quant1x/level1/hello2.py
quant1x/level1/helpers.py
quant1x/level1/minute_time.py
quant1x/level1/protocol.py
quant1x/level1/security_bars.py
quant1x/level1/security_count.py
quant1x/level1/security_list.py
quant1x/level1/security_quote.py
quant1x/level1/transaction.py
quant1x/level1/xdxr_info.py
quant1x/log/__init__.py
quant1x/log/logger.py
quant1x/net/__init__.py
quant1x/net/connection_pool.py
quant1x/net/endpoint.py
quant1x/net/operation_handler.py
quant1x/std/__init__.py
quant1x/std/pattern.py
quant1x/std/time.py
quant1x/util/__init__.py
quant1x/util/chart.py
quant1x/util/font.py
quant1x-0.7.5.dist-info/licenses/LICENSE
quant1x-0.7.5.dist-info/METADATA
quant1x-0.7.5.dist-info/WHEEL
quant1x-0.7.5.dist-info/top_level.txt
quant1x-0.7.5.dist-info/RECORD
