Metadata-Version: 2.4
Name: quant1x
Version: 0.7.5
Summary: Quant1X量化研究
Home-page: https://gitee.com/quant1x/quant1x
Author: wangfeng
Author-email: wangfengxy@sina.cn
License: Apache 2.0 license
Keywords: quant1x python
Classifier: Development Status :: 2 - Pre-Alpha
Classifier: Intended Audience :: Developers
Classifier: License :: OSI Approved :: MIT License
Classifier: Natural Language :: English
Classifier: Programming Language :: Python :: 3
Classifier: Programming Language :: Python :: 3.8
Classifier: Programming Language :: Python :: 3.9
Classifier: Programming Language :: Python :: 3.10
Classifier: Programming Language :: Python :: 3.11
Classifier: Programming Language :: Python :: 3.12
Classifier: Programming Language :: Python :: 3.13
Classifier: Programming Language :: Python :: 3.14
License-File: LICENSE
Requires-Dist: setuptools~=78.0.0
Requires-Dist: twine~=6.1.0
Requires-Dist: wheel~=0.45.1
Requires-Dist: requests-toolbelt~=1.0.0
Requires-Dist: loguru~=0.7.3
Requires-Dist: icecream~=2.1.5
Requires-Dist: PyYAML~=6.0.2
Requires-Dist: numpy~=2.3.0
Requires-Dist: pandas~=2.3.0
Requires-Dist: numba~=0.62.1
Requires-Dist: gitpython~=3.1.44
Requires-Dist: python-dateutil~=2.9.0.post0
Requires-Dist: matplotlib~=3.10.5
Requires-Dist: akshare~=1.17.38
Requires-Dist: findpeaks~=2.7.4
Requires-Dist: mootdx~=0.11.7
Requires-Dist: python-dateutil~=2.9.0.post0
Requires-Dist: requests==2.32.0
Requires-Dist: tqdm~=4.67.1
Requires-Dist: xgboost~=3.0.0
Requires-Dist: scikit-learn~=1.7.1
Requires-Dist: matplotlib~=3.10.1
Requires-Dist: scipy~=1.16.0
Requires-Dist: caerus~=1.0.1
Requires-Dist: joblib~=1.5.1
Requires-Dist: inflection~=0.5.1
Dynamic: author
Dynamic: author-email
Dynamic: classifier
Dynamic: description
Dynamic: description-content-type
Dynamic: home-page
Dynamic: keywords
Dynamic: license
Dynamic: license-file
Dynamic: requires-dist
Dynamic: summary
